containernet/__init__.py
containernet/clean.py
containernet/cli.py
containernet/link.py
containernet/net.py
containernet/node.py
containernet/nodelib.py
containernet/term.py
containernet/util.py
experiment/__init__.py
experiment/constants.py
experiment/deploy_lft.py
experiment/deploy_mininet.py
experiment/emu_emu_wired.py
experiment/emu_emu_wireless.py
experiment/emu_emu_wireless_old.py
experiment/emu_phy_wired.py
experiment/emu_phy_wireless.py
experiment/experiment.py
experiment/measure_deploy_time.py
experiment/measure_mininet_deploy_time.py
experiment/pschedulerWrapper.py
experiment/simpleSDNTopology.py
experiment/wired_experiment.py
experiment/wireless_experiment.py
profissa_lft/__init__.py
profissa_lft/cicflowmeter.py
profissa_lft/constants.py
profissa_lft/controller.py
profissa_lft/enb.py
profissa_lft/epc.py
profissa_lft/exceptions.py
profissa_lft/host.py
profissa_lft/node.py
profissa_lft/perfsonar.py
profissa_lft/switch.py
profissa_lft/ue.py
profissa_lft-1.0.9.dist-info/LICENSE
profissa_lft-1.0.9.dist-info/METADATA
profissa_lft-1.0.9.dist-info/WHEEL
profissa_lft-1.0.9.dist-info/top_level.txt
profissa_lft-1.0.9.dist-info/RECORD
